pypply/__init__.py
pypply/api.py
pypply/geography.py
pypply/smart.py
pypply/utils.py
pypply/version.py
pypply/mode_types/__init__.py
pypply/mode_types/air.py
pypply/mode_types/commons.py
pypply/mode_types/road_emea.py
pypply/mode_types/road_na.py
pypply/mode_types/sea_longterm.py
pypply-1.0.0.dist-info/licenses/LICENSE
pypply-1.0.0.dist-info/WHEEL
pypply-1.0.0.dist-info/METADATA
pypply-1.0.0.dist-info/RECORD
