Metadata-Version: 2.4
Name: pypply
Version: 1.0.0
Summary: Makes it easier to use Upply API
Keywords: transport,upply,benchmark,freight,smart,supply-chain,api,python
Author-email: Baptiste Rebours <baptiste.rebours@upply.com>
Requires-Python: >=3.9
Classifier: Intended Audience :: Developers
Classifier: Intended Audience :: Science/Research
Classifier: Programming Language :: Python
Classifier: Operating System :: OS Independent
Classifier: Topic :: Software Development :: Libraries :: Python Modules
Classifier: License :: OSI Approved :: MIT License
License-File: LICENSE
Requires-Dist: pandas>=2.3.1
Requires-Dist: pydantic>=2.11.7
Requires-Dist: requests>=2.32.4
Requires-Dist: flit>=3.12.0 ; extra == "dev"
Requires-Dist: isort>=6.0.1 ; extra == "dev"
Requires-Dist: pyink>=24.10.1 ; extra == "dev"
Requires-Dist: pylint>=3.3.8 ; extra == "dev"
Requires-Dist: myst-parser>=3.0.1 ; extra == "docs"
Requires-Dist: sphinx ; extra == "docs"
Requires-Dist: sphinx-autodoc-typehints>=2.3.0 ; extra == "docs"
Requires-Dist: sphinx-markdown-builder>=0.6.8 ; extra == "docs"
Requires-Dist: dotenv>=0.9.9 ; extra == "test"
Requires-Dist: pytest>=8.3.4 ; extra == "test"
Project-URL: documentation, https://developers.upply.com/docs/pypply/
Project-URL: homepage, https://developers.upply.com/docs/pypply/
Project-URL: repository, https://github.com/upply-labs/pypply
Provides-Extra: dev
Provides-Extra: docs
Provides-Extra: test
